{
  "prefix": ".",
  "diabledCommands": [
    "say",
    "export",
    "load",
    "save"
  ],
  "chatter": {
    "randomChat": 0.98,
    "randomDouble": 0.8,
    "arrayLimiter": 75000,
    "useHonk": false,
    "messageSplitter": "[\n.;()]",
    "minimumScore": 2,
    "maxTries": 30,
    "disabledChannels": [
      "admin"
    ],
    "sentence": {
      "maxTries": 20
    },
    "corpus": {
      "stateSize": 2
    }
  },
  "kick": {
    "requiredVotes": 5,
    "enabled": false,
    "voteTime": 60000
  },
  "curse": {
    "requiredVotes": 5,
    "enabled": false,
    "voteTime": 60000
  }
}